pydbmodels/__init__.py
pydbmodels/settings.py
pydbmodels/generators/__init__.py
pydbmodels/generators/generator.py
pydbmodels/generators/pydantic/__init__.py
pydbmodels/generators/pydantic/generator.py
pydbmodels/generators/pydantic/type_map.py
pydbmodels/generators/templates/__init__.py
pydbmodels/generators/templates/_schema_init_file_templates.j2
pydbmodels/generators/templates/_table_templates.j2
pydbmodels/generators/templates/_user_defined_templates.j2
pydbmodels/generators/templates/models.py
pydbmodels/generators/types/__init__.py
pydbmodels/generators/types/_types.py
pydbmodels-0.0.10.dist-info/METADATA
pydbmodels-0.0.10.dist-info/WHEEL
pydbmodels-0.0.10.dist-info/licenses/LICENSE
pydbmodels-0.0.10.dist-info/RECORD
