Metadata-Version: 2.1
Name: pydbmodels
Version: 0.0.10
Summary: Creates database models from a database
Author-email: Francesco Vertemati <verte.fra@gmail.com>
License-File: LICENSE
Classifier: Programming Language :: Python :: 3
Requires-Dist: black>=22.10.0
Requires-Dist: dbmeta>=0.0.10
Requires-Dist: jinja2>=3.1.2
Provides-Extra: lint
Requires-Dist: black==22.10.0; extra == 'lint'
Requires-Dist: mypy==0.990; extra == 'lint'
Provides-Extra: test
Requires-Dist: psycopg>=3.1.4; extra == 'test'
Requires-Dist: pydantic>=1.10.2; extra == 'test'
Requires-Dist: pytest-cov==4.0.0; extra == 'test'
Requires-Dist: pytest==7.2.0; extra == 'test'
